Metadata-Version: 1.0
Name: distributions-mmbader
Version: 1.0
Summary: Gaussian distributions
Home-page: UNKNOWN
Author: Michael Bader
Author-email: UNKNOWN
License: UNKNOWN
Platform: UNKNOWN
